voice_agent/__init__.py
voice_agent/voice_agent.py
voice_agent/voice_agent2.py
voice_agent/gather/__init__.py
voice_agent/gather/base.py
voice_agent/gather/read.py
voice_agent/gather/vector_read.py
voice_agent/llm/__init__.py
voice_agent/llm/base.py
voice_agent/llm/claude_llm.py
voice_agent/llm/custom_llm.py
voice_agent/llm/factory.py
voice_agent/llm/gemini_demo.py
voice_agent/llm/gemini_llm.py
voice_agent/llm/mistral_llm.py
voice_agent/llm/ollma_llm.py
voice_agent/llm/openai_llm.py
voice_agent/llm/openrouter_service_llm.py
voice_agent/llm/package_demo.py
voice_agent/stt/__init__.py
voice_agent/stt/base.py
voice_agent/stt/check_audio_devices.py
voice_agent/stt/google_stt.py
voice_agent/stt/speech_to_text.py
voice_agent/stt/whisper_stt.py
voice_agent/tts/__init__.py
voice_agent/tts/base.py
voice_agent/tts/evenlabs_tts.py
voice_agent/utils/__init__.py
voice_agent/utils/audio_io.py
voice_agent/utils/emotions.py
voice_agent/utils/language.py
voice_agent_tequity-0.1.1.dist-info/METADATA
voice_agent_tequity-0.1.1.dist-info/WHEEL
voice_agent_tequity-0.1.1.dist-info/top_level.txt
voice_agent_tequity-0.1.1.dist-info/RECORD
