Metadata-Version: 2.4
Name: voice-agent-tequity
Version: 0.1.1
Summary: A voice agent framework for LLM + STT + TTS pipelines
Author: Ravi Kishan
Author-email: kishanravi887321@gmail.com
Requires-Python: >=3.8
Requires-Dist: aiohappyeyeballs==2.6.1
Requires-Dist: aiohttp==3.12.15
Requires-Dist: aiosignal==1.4.0
Requires-Dist: aiosqlite==0.21.0
Requires-Dist: annotated-types==0.7.0
Requires-Dist: anyio==4.10.0
Requires-Dist: async-timeout==5.0.1
Requires-Dist: attrs==25.3.0
Requires-Dist: banks==2.2.0
Requires-Dist: beautifulsoup4==4.13.5
Requires-Dist: certifi==2025.8.3
Requires-Dist: cffi==1.17.1
Requires-Dist: charset-normalizer==3.4.3
Requires-Dist: click==8.2.1
Requires-Dist: colorama==0.4.6
Requires-Dist: dataclasses-json==0.6.7
Requires-Dist: defusedxml==0.7.1
Requires-Dist: Deprecated==1.2.18
Requires-Dist: dirtyjson==1.0.8
Requires-Dist: distro==1.9.0
Requires-Dist: elevenlabs==2.13.0
Requires-Dist: exceptiongroup==1.3.0
Requires-Dist: filelock==3.19.1
Requires-Dist: filetype==1.2.0
Requires-Dist: frozenlist==1.7.0
Requires-Dist: fsspec==2025.7.0
Requires-Dist: greenlet==3.2.4
Requires-Dist: griffe==1.13.0
Requires-Dist: h11==0.16.0
Requires-Dist: httpcore==1.0.9
Requires-Dist: httpx==0.28.1
Requires-Dist: huggingface-hub==0.34.4
Requires-Dist: idna==3.10
Requires-Dist: Jinja2==3.1.6
Requires-Dist: jiter==0.10.0
Requires-Dist: joblib==1.5.2
Requires-Dist: llama-cloud==0.1.35
Requires-Dist: llama-cloud-services==0.6.54
Requires-Dist: llama-index==0.13.3
Requires-Dist: llama-index-cli==0.5.0
Requires-Dist: llama-index-core==0.13.3
Requires-Dist: llama-index-embeddings-huggingface==0.6.0
Requires-Dist: llama-index-embeddings-openai==0.5.0
Requires-Dist: llama-index-indices-managed-llama-cloud==0.9.2
Requires-Dist: llama-index-instrumentation==0.4.0
Requires-Dist: llama-index-llms-openai==0.5.4
Requires-Dist: llama-index-readers-file==0.5.2
Requires-Dist: llama-index-readers-llama-parse==0.5.0
Requires-Dist: llama-index-workflows==1.3.0
Requires-Dist: llama-parse==0.6.54
Requires-Dist: MarkupSafe==3.0.2
Requires-Dist: marshmallow==3.26.1
Requires-Dist: mpmath==1.3.0
Requires-Dist: multidict==6.6.4
Requires-Dist: mypy_extensions==1.1.0
Requires-Dist: nest-asyncio==1.6.0
Requires-Dist: networkx==3.4.2
Requires-Dist: nltk==3.9.1
Requires-Dist: numpy==2.2.6
Requires-Dist: openai==1.102.0
Requires-Dist: packaging==24.2
Requires-Dist: pandas==2.2.3
Requires-Dist: pillow==11.3.0
Requires-Dist: pinecone==7.3.0
Requires-Dist: pinecone-plugin-assistant==1.7.0
Requires-Dist: pinecone-plugin-interface==0.0.7
Requires-Dist: platformdirs==4.4.0
Requires-Dist: propcache==0.3.2
Requires-Dist: PyAudio==0.2.14
Requires-Dist: pycparser==2.22
Requires-Dist: pydantic==2.11.7
Requires-Dist: pydantic_core==2.33.2
Requires-Dist: pypdf==6.0.0
Requires-Dist: PyPDF2==3.0.1
Requires-Dist: python-dateutil==2.9.0.post0
Requires-Dist: python-dotenv==1.1.1
Requires-Dist: pytz==2025.2
Requires-Dist: PyYAML==6.0.2
Requires-Dist: regex==2025.8.29
Requires-Dist: requests==2.32.5
Requires-Dist: safetensors==0.6.2
Requires-Dist: scikit-learn==1.7.1
Requires-Dist: scipy==1.15.3
Requires-Dist: sentence-transformers==5.1.0
Requires-Dist: six==1.17.0
Requires-Dist: sniffio==1.3.1
Requires-Dist: sounddevice==0.5.2
Requires-Dist: soupsieve==2.8
Requires-Dist: SQLAlchemy==2.0.43
Requires-Dist: srt==3.5.3
Requires-Dist: striprtf==0.0.26
Requires-Dist: sympy==1.14.0
Requires-Dist: tenacity==9.1.2
Requires-Dist: threadpoolctl==3.6.0
Requires-Dist: tiktoken==0.11.0
Requires-Dist: tokenizers==0.22.0
Requires-Dist: torch==2.8.0
Requires-Dist: tqdm==4.67.1
Requires-Dist: transformers==4.56.0
Requires-Dist: typing-inspect==0.9.0
Requires-Dist: typing-inspection==0.4.1
Requires-Dist: typing_extensions==4.15.0
Requires-Dist: tzdata==2025.2
Requires-Dist: urllib3==2.5.0
Requires-Dist: vosk==0.3.45
Requires-Dist: websocket-client==1.8.0
Requires-Dist: websockets==15.0.1
Requires-Dist: wrapt==1.17.3
Requires-Dist: yarl==1.20.1
Dynamic: author
Dynamic: author-email
Dynamic: requires-dist
Dynamic: requires-python
Dynamic: summary
